{
  "name": "Minimal Markdown",
  "content_type": "SN|Component",
  "main": "index.html",
  "area": "editor-editor",
  "spellcheckControl": true,
  "note_type": "markdown",
  "file_type": "md",
  "showInGallery": true,
  "identifier": "com.sncommunity.minimal-markdown",
  "version": "1.4.2",
  "url": "https://standardnotes.github.io/plugins/cdn/dist/static/com.sncommunity.minimal-markdown/index.html",
  "download_url": "https://standardnotes.github.io/plugins/cdn/dist/zips/com.sncommunity.minimal-markdown.zip",
  "latest_url": "https://standardnotes.github.io/plugins/cdn/dist/entries/com.sncommunity.minimal-markdown.json",
  "publisher": "Standard Notes Community",
  "description": "A minimal Markdown editor with live rendering and in-text search via Ctrl/Cmd + F",
  "base64Hash": "a13034ff3ccab3acd12cc130c7a0216449755ef2a71fec577c871a22a12fa8d5",
  "binaryHash": "5b161a49cc2582403d392d36e337e6d12059a173def1445ceb5c42b01707207c"
}