{
  "name": "Bold Editor",
  "content_type": "SN|Component",
  "area": "editor-editor",
  "spellcheckControl": true,
  "note_type": "rich-text",
  "main": "dist/index.html",
  "file_type": "html",
  "showInGallery": false,
  "identifier": "com.sncommunity.bold-editor",
  "version": "1.7.7",
  "url": "https://standardnotes.github.io/plugins/cdn/dist/static/com.sncommunity.bold-editor/dist/index.html",
  "download_url": "https://standardnotes.github.io/plugins/cdn/dist/zips/com.sncommunity.bold-editor.zip",
  "latest_url": "https://standardnotes.github.io/plugins/cdn/dist/entries/com.sncommunity.bold-editor.json",
  "publisher": "Standard Notes Retired",
  "description": "A simple and peaceful rich editor that helps you write and think clearly.",
  "base64Hash": "cf939330175fbc9fd5c71b563b144805ef5c1dcc905c33aac404f821b288fcea",
  "binaryHash": "a46991583cc909f00ef46ba9fc384a9ae74cfa9177d22b0afe853126a3222e50"
}