{
  "name": "Basic Markdown",
  "content_type": "SN|Component",
  "area": "editor-editor",
  "spellcheckControl": true,
  "note_type": "markdown",
  "main": "dist/index.html",
  "file_type": "md",
  "showInGallery": true,
  "identifier": "com.sncommunity.markdown-basic",
  "version": "1.7.6",
  "url": "https://standardnotes.github.io/plugins/cdn/dist/static/com.sncommunity.markdown-basic/dist/index.html",
  "download_url": "https://standardnotes.github.io/plugins/cdn/dist/zips/com.sncommunity.markdown-basic.zip",
  "latest_url": "https://standardnotes.github.io/plugins/cdn/dist/entries/com.sncommunity.markdown-basic.json",
  "publisher": "Standard Notes Community",
  "description": "A Markdown editor with dynamic split-pane preview.",
  "base64Hash": "6f23ea6b4f9176350f96c904ff778ecf385e14fc453a37aa551e3860463a2614",
  "binaryHash": "e1a1930fe391365498af5656b0e179f6a90420e417f6bddf25e59529caad6c7d"
}